typenum/__init__.py
typenum/core.py
typenum/py.typed
typenum/pydantic/__init__.py
typenum/pydantic/core.py
typenum/pydantic/serialization/__init__.py
typenum/pydantic/serialization/adjacently.py
typenum/pydantic/serialization/externally.py
typenum/pydantic/serialization/internally.py
typenum/pydantic/serialization/tagged.py
typenum-0.3.2.dist-info/LICENSE
typenum-0.3.2.dist-info/METADATA
typenum-0.3.2.dist-info/WHEEL
typenum-0.3.2.dist-info/RECORD
