Metadata-Version: 2.1
Name: typenum
Version: 0.3.2
Summary: Type-containing enumeration
Home-page: https://github.com/rjotanm/typenum
License: MIT
Author: Rinat Balbekov
Author-email: me@rjotanm.dev
Requires-Python: >=3.10,<4.0
Classifier: Development Status :: 3 - Alpha
Classifier: Framework :: Pydantic
Classifier: Framework :: Pydantic :: 2
Classifier: Intended Audience :: Developers
Classifier: License :: OSI Approved :: MIT License
Classifier: Programming Language :: Python
Classifier: Programming Language :: Python :: 3
Classifier: Programming Language :: Python :: 3.10
Classifier: Programming Language :: Python :: 3.11
Classifier: Programming Language :: Python :: 3.12
Classifier: Programming Language :: Python :: 3.13
Classifier: Topic :: Software Development :: Libraries :: Python Modules
Classifier: Typing :: Typed
Provides-Extra: pydantic
Requires-Dist: pydantic (>=2.9.0) ; extra == "pydantic"
Requires-Dist: typing-extensions (>=4.0.0)
Project-URL: Repository, https://github.com/rjotanm/typenum
